filesize_cli/__init__.py
filesize_cli/main.py
tests/__init__.py
tests/test_main.py
filesize_cli-1.1.1.dist-info/LICENSE
filesize_cli-1.1.1.dist-info/METADATA
filesize_cli-1.1.1.dist-info/WHEEL
filesize_cli-1.1.1.dist-info/entry_points.txt
filesize_cli-1.1.1.dist-info/top_level.txt
filesize_cli-1.1.1.dist-info/RECORD
