Metadata-Version: 2.1
Name: filesize-cli
Version: 1.1.1
Summary: Calculate file and directory sizes from the command line.
Home-page: https://www.kolja-nolte.com 
Author: Kolja Nolte
Author-email: Kolja Nolte <kolja.nolte@gmail.com>
License: MIT
Project-URL: Homepage, https://www.kolja-nolte.com
Classifier: Programming Language :: Python :: 3
Classifier: License :: OSI Approved :: MIT License
Classifier: Operating System :: OS Independent
Requires-Python: >=3.6
License-File: LICENSE
